codewatchman/Watchman.py
codewatchman/WatchmanLog.py
codewatchman/__init__.py
codewatchman-0.1.3.dist-info/LICENSE
codewatchman-0.1.3.dist-info/METADATA
codewatchman-0.1.3.dist-info/WHEEL
codewatchman-0.1.3.dist-info/top_level.txt
codewatchman-0.1.3.dist-info/RECORD
