Metadata-Version: 2.1
Name: codewatchman
Version: 0.1.3
Summary: Code Watchman Python API.
Home-page: https://github.com/thevishnupradeep/CWMPythonLibrary
Author: Code Watchman
Author-email: codewatchmanapp@gmail.com
License: MIT
Download-URL: https://github.com/thevishnupradeep/CWMPythonLibrary/archive/v0.0.1.tar.gz
Keywords: code watchman,codewatchman,watchman
Platform: UNKNOWN
Classifier: Programming Language :: Python :: 3
Classifier: Operating System :: OS Independent
Classifier: License :: OSI Approved :: MIT License
Classifier: Intended Audience :: Developers
Requires-Python: >=3.4
Requires-Dist: requests
